{
"type": "FeatureCollection",
"name": "alabama_centroids",
"crs": { "type": "name", "properties": { "name": "urn:ogc:def:crs:OGC:1.3:CRS84" } },
"features": [
{ "type": "Feature", "properties": { "NAME": "Poarch Creek" }, "geometry": { "type": "Point", "coordinates": [ -86.20914822972837, 32.528463251967167 ] } },
{ "type": "Feature", "properties": { "NAME": "Poarch Creek" }, "geometry": { "type": "Point", "coordinates": [ -87.481726329718541, 31.102623724017342 ] } },
{ "type": "Feature", "properties": { "NAME": "Poarch Creek" }, "geometry": { "type": "Point", "coordinates": [ -87.554402695313641, 31.097085942866734 ] } },
{ "type": "Feature", "properties": { "NAME": "Poarch Creek" }, "geometry": { "type": "Point", "coordinates": [ -87.558792619178504, 31.1004397615296 ] } },
{ "type": "Feature", "properties": { "NAME": "Poarch Creek" }, "geometry": { "type": "Point", "coordinates": [ -87.566569656577329, 31.10487628285793 ] } },
{ "type": "Feature", "properties": { "NAME": "MOWA Choctaw" }, "geometry": { "type": "Point", "coordinates": [ -88.048007424157504, 31.140219446276539 ] } },
{ "type": "Feature", "properties": { "NAME": "MOWA Choctaw" }, "geometry": { "type": "Point", "coordinates": [ -88.05326076609002, 31.147910993168296 ] } },
{ "type": "Feature", "properties": { "NAME": "MOWA Choctaw" }, "geometry": { "type": "Point", "coordinates": [ -88.092596147520794, 31.277103115531649 ] } },
{ "type": "Feature", "properties": { "NAME": "Poarch Creek" }, "geometry": { "type": "Point", "coordinates": [ -86.139927536745077, 32.42650133435906 ] } },
{ "type": "Feature", "properties": { "NAME": "Poarch Creek" }, "geometry": { "type": "Point", "coordinates": [ -87.433694979575208, 31.36441045785033 ] } },
{ "type": "Feature", "properties": { "NAME": "Poarch Creek" }, "geometry": { "type": "Point", "coordinates": [ -87.481017712584844, 31.10378662956364 ] } },
{ "type": "Feature", "properties": { "NAME": "Poarch Creek" }, "geometry": { "type": "Point", "coordinates": [ -87.484995969324942, 31.071554778038259 ] } },
{ "type": "Feature", "properties": { "NAME": "Poarch Creek" }, "geometry": { "type": "Point", "coordinates": [ -87.561624036519945, 31.099014375607599 ] } },
{ "type": "Feature", "properties": { "NAME": "Star Muskogee Creek" }, "geometry": { "type": "Point", "coordinates": [ -85.969331767618371, 31.72679578647146 ] } },
{ "type": "Feature", "properties": { "NAME": "Cher-O-Creek" }, "geometry": { "type": "Point", "coordinates": [ -85.282992468844, 31.162409608232412 ] } },
{ "type": "Feature", "properties": { "NAME": "Cherokee Tribe of Northeast Alabama" }, "geometry": { "type": "Point", "coordinates": [ -86.208137238830759, 34.262663895734768 ] } },
{ "type": "Feature", "properties": { "NAME": "Cherokee Tribe of Northeast Alabama" }, "geometry": { "type": "Point", "coordinates": [ -86.216611142209402, 34.569083364286087 ] } },
{ "type": "Feature", "properties": { "NAME": "Cherokee Tribe of Northeast Alabama" }, "geometry": { "type": "Point", "coordinates": [ -86.310750864832499, 34.208327952016241 ] } },
{ "type": "Feature", "properties": { "NAME": "Cherokee Tribe of Northeast Alabama" }, "geometry": { "type": "Point", "coordinates": [ -86.504070355513988, 34.329353210650773 ] } },
{ "type": "Feature", "properties": { "NAME": "Echota Cherokee" }, "geometry": { "type": "Point", "coordinates": [ -86.423226581149038, 34.588080049229447 ] } },
{ "type": "Feature", "properties": { "NAME": "Echota Cherokee" }, "geometry": { "type": "Point", "coordinates": [ -86.433819204720493, 34.863813626635604 ] } },
{ "type": "Feature", "properties": { "NAME": "Echota Cherokee" }, "geometry": { "type": "Point", "coordinates": [ -86.734876096764154, 34.833759262097978 ] } },
{ "type": "Feature", "properties": { "NAME": "Echota Cherokee" }, "geometry": { "type": "Point", "coordinates": [ -86.902649436835972, 34.300711862458151 ] } },
{ "type": "Feature", "properties": { "NAME": "Echota Cherokee" }, "geometry": { "type": "Point", "coordinates": [ -87.29848477681297, 34.484511226352701 ] } },
{ "type": "Feature", "properties": { "NAME": "MaChis Lower Creek" }, "geometry": { "type": "Point", "coordinates": [ -85.518732631469462, 31.208109605990966 ] } },
{ "type": "Feature", "properties": { "NAME": "MaChis Lower Creek" }, "geometry": { "type": "Point", "coordinates": [ -85.620984121423831, 31.207135642246207 ] } },
{ "type": "Feature", "properties": { "NAME": "MaChis Lower Creek" }, "geometry": { "type": "Point", "coordinates": [ -86.010673554366505, 31.341732390141384 ] } },
{ "type": "Feature", "properties": { "NAME": "United Cherokee Ani-Yun-Wiya Nation" }, "geometry": { "type": "Point", "coordinates": [ -86.148160822948071, 34.29485511713726 ] } },
{ "type": "Feature", "properties": { "NAME": "United Cherokee Ani-Yun-Wiya Nation" }, "geometry": { "type": "Point", "coordinates": [ -86.323528363368851, 34.323596533933255 ] } }
]
}
