{
"type": "FeatureCollection",
"name": "delaware_centroids",
"crs": { "type": "name", "properties": { "name": "urn:ogc:def:crs:OGC:1.3:CRS84" } },
"features": [
{ "type": "Feature", "properties": { "NAME": "Lenape Indian Tribe of Delaware" }, "geometry": { "type": "Point", "coordinates": [ -75.570016203507151, 39.197944078148517 ] } },
{ "type": "Feature", "properties": { "NAME": "Lenape Indian Tribe of Delaware" }, "geometry": { "type": "Point", "coordinates": [ -75.577384632826991, 39.222715272593575 ] } },
{ "type": "Feature", "properties": { "NAME": "Lenape Indian Tribe of Delaware" }, "geometry": { "type": "Point", "coordinates": [ -75.596017656977423, 39.207588471743151 ] } },
{ "type": "Feature", "properties": { "NAME": "Nanticoke Indian Tribe" }, "geometry": { "type": "Point", "coordinates": [ -75.215163585947039, 38.653990859179096 ] } }
]
}
