{
"type": "FeatureCollection",
"name": "delaware_centroids",
"crs": { "type": "name", "properties": { "name": "urn:ogc:def:crs:OGC:1.3:CRS84" } },
"features": [
{ "type": "Feature", "properties": { "NAME": "Nanticoke Indian Tribe" }, "geometry": { "type": "Point", "coordinates": [ -75.215531667885415, 38.652671951900274 ] } },
{ "type": "Feature", "properties": { "NAME": "Lenape Indian Tribe of Delaware" }, "geometry": { "type": "Point", "coordinates": [ -75.596003953306095, 39.207599597786434 ] } },
{ "type": "Feature", "properties": { "NAME": "Lenape Indian Tribe of Delaware" }, "geometry": { "type": "Point", "coordinates": [ -75.570017255121584, 39.197945442456344 ] } },
{ "type": "Feature", "properties": { "NAME": "Lenape Indian Tribe of Delaware" }, "geometry": { "type": "Point", "coordinates": [ -75.577394678699847, 39.222713588444918 ] } }
]
}
