{
"type": "FeatureCollection",
"name": "ca_riverside_centroids",
"crs": { "type": "name", "properties": { "name": "urn:ogc:def:crs:OGC:1.3:CRS84" } },
"features": [
{ "type": "Feature", "properties": { "Neighborho": "Casa Blanca" }, "geometry": { "type": "Point", "coordinates": [ -117.399148140384725, 33.932699337624989 ] } },
{ "type": "Feature", "properties": { "Neighborho": "Hawarden Hills" }, "geometry": { "type": "Point", "coordinates": [ -117.374749825909234, 33.93254982287084 ] } },
{ "type": "Feature", "properties": { "Neighborho": "Orangecrest" }, "geometry": { "type": "Point", "coordinates": [ -117.322207119237959, 33.887172732796145 ] } },
{ "type": "Feature", "properties": { "Neighborho": "La Sierra" }, "geometry": { "type": "Point", "coordinates": [ -117.486507395489312, 33.911093914118936 ] } },
{ "type": "Feature", "properties": { "Neighborho": "Northside" }, "geometry": { "type": "Point", "coordinates": [ -117.361773829047067, 34.007648501982921 ] } },
{ "type": "Feature", "properties": { "Neighborho": "La Sierra Hills" }, "geometry": { "type": "Point", "coordinates": [ -117.507678512373289, 33.937216758300785 ] } },
{ "type": "Feature", "properties": { "Neighborho": "Victoria" }, "geometry": { "type": "Point", "coordinates": [ -117.369616595786511, 33.949679805409076 ] } },
{ "type": "Feature", "properties": { "Neighborho": "Airport" }, "geometry": { "type": "Point", "coordinates": [ -117.442458931129096, 33.955730713729942 ] } },
{ "type": "Feature", "properties": { "Neighborho": "Grand" }, "geometry": { "type": "Point", "coordinates": [ -117.412320926009315, 33.967557237610613 ] } },
{ "type": "Feature", "properties": { "Neighborho": "University" }, "geometry": { "type": "Point", "coordinates": [ -117.328319693920335, 33.977581782732244 ] } },
{ "type": "Feature", "properties": { "Neighborho": "Ramona" }, "geometry": { "type": "Point", "coordinates": [ -117.430431263965374, 33.936039130974457 ] } },
{ "type": "Feature", "properties": { "Neighborho": "Arlington" }, "geometry": { "type": "Point", "coordinates": [ -117.450107534934148, 33.921423991874143 ] } },
{ "type": "Feature", "properties": { "Neighborho": "Arlington Heights" }, "geometry": { "type": "Point", "coordinates": [ -117.410287661223791, 33.903156644084163 ] } },
{ "type": "Feature", "properties": { "Neighborho": "Presidential Park" }, "geometry": { "type": "Point", "coordinates": [ -117.419988433900784, 33.921102050118286 ] } },
{ "type": "Feature", "properties": { "Neighborho": "Magnolia Center" }, "geometry": { "type": "Point", "coordinates": [ -117.39959920420462, 33.951562227687944 ] } },
{ "type": "Feature", "properties": { "Neighborho": "La Sierra South" }, "geometry": { "type": "Point", "coordinates": [ -117.474638731144793, 33.893185186222127 ] } },
{ "type": "Feature", "properties": { "Neighborho": "Eastside" }, "geometry": { "type": "Point", "coordinates": [ -117.361474631138762, 33.971258791637148 ] } },
{ "type": "Feature", "properties": { "Neighborho": "Arlington South" }, "geometry": { "type": "Point", "coordinates": [ -117.442545782342279, 33.907242984940439 ] } },
{ "type": "Feature", "properties": { "Neighborho": "Mission Grove" }, "geometry": { "type": "Point", "coordinates": [ -117.324317252680387, 33.917142369921059 ] } },
{ "type": "Feature", "properties": { "Neighborho": "Sycamore Canyon Park" }, "geometry": { "type": "Point", "coordinates": [ -117.316806888643399, 33.936023409920793 ] } },
{ "type": "Feature", "properties": { "Neighborho": "Wood Streets" }, "geometry": { "type": "Point", "coordinates": [ -117.390660338861053, 33.96727640107104 ] } },
{ "type": "Feature", "properties": { "Neighborho": "Hunter Industrial Park" }, "geometry": { "type": "Point", "coordinates": [ -117.338714570009557, 33.998543669535934 ] } },
{ "type": "Feature", "properties": { "Neighborho": "La Sierra Acres" }, "geometry": { "type": "Point", "coordinates": [ -117.490408369211082, 33.945091346310065 ] } },
{ "type": "Feature", "properties": { "Neighborho": "Arlanza" }, "geometry": { "type": "Point", "coordinates": [ -117.466567318077551, 33.942566767175258 ] } },
{ "type": "Feature", "properties": { "Neighborho": "Alessandro Heights" }, "geometry": { "type": "Point", "coordinates": [ -117.360787104634738, 33.913240765910167 ] } },
{ "type": "Feature", "properties": { "Neighborho": "Downtown" }, "geometry": { "type": "Point", "coordinates": [ -117.37951095114795, 33.98739675312067 ] } },
{ "type": "Feature", "properties": { "Neighborho": "Sycamore Canyon/Canyon Springs" }, "geometry": { "type": "Point", "coordinates": [ -117.294054233572894, 33.932621497936815 ] } },
{ "type": "Feature", "properties": { "Neighborho": "Canyon Crest" }, "geometry": { "type": "Point", "coordinates": [ -117.337292041359674, 33.942399813213882 ] } }
]
}
